z3c/rml/README.txt
z3c/rml/__init__.py
z3c/rml/attr.py
z3c/rml/canvas.py
z3c/rml/chart.py
z3c/rml/directive.py
z3c/rml/doclogic.py
z3c/rml/document.py
z3c/rml/dtd.py
z3c/rml/flowable.py
z3c/rml/form.py
z3c/rml/interfaces.py
z3c/rml/list.py
z3c/rml/num2words.py
z3c/rml/occurence.py
z3c/rml/page.py
z3c/rml/pagetemplate.py
z3c/rml/pagetemplate.txt
z3c/rml/paraparser.py
z3c/rml/pdfinclude.py
z3c/rml/platypus.py
z3c/rml/reference.pt
z3c/rml/reference.py
z3c/rml/rlfix.py
z3c/rml/rml-reference.pdf
z3c/rml/rml.dtd
z3c/rml/rml2pdf.py
z3c/rml/rml2pdfscript.py
z3c/rml/special.py
z3c/rml/storyplace.py
z3c/rml/stylesheet.py
z3c/rml/template.py
z3c/rml/tests/__init__.py
z3c/rml/tests/flowable.py
z3c/rml/tests/module.py
z3c/rml/tests/test_directive.py
z3c/rml/tests/test_dtd.py
z3c/rml/tests/test_num2words.py
z3c/rml/tests/test_pagetemplate.py
z3c/rml/tests/test_reference.py
z3c/rml/tests/test_rml.py
z3c/rml/tests/test_rml2pdf.py
z3c/rml/tests/test_subprocess.py
z3c/rml/tests/expected/encoding-test-latin1.pdf
z3c/rml/tests/expected/encoding-test-utf8.pdf
z3c/rml/tests/expected/printScaling.pdf
z3c/rml/tests/expected/rml-examples-000-simple.pdf
z3c/rml/tests/expected/rml-examples-001-cmbox.pdf
z3c/rml/tests/expected/rml-examples-001-hello.pdf
z3c/rml/tests/expected/rml-examples-002-paras.pdf
z3c/rml/tests/expected/rml-examples-003-frames.pdf
z3c/rml/tests/expected/rml-examples-004-fpt-templates.pdf
z3c/rml/tests/expected/rml-examples-004-templates.pdf
z3c/rml/tests/expected/rml-examples-005-fonts.pdf
z3c/rml/tests/expected/rml-examples-006-barcodes.pdf
z3c/rml/tests/expected/rml-examples-008-tables.pdf
z3c/rml/tests/expected/rml-examples-009-splitting.pdf
z3c/rml/tests/expected/rml-examples-010-linkURL.pdf
z3c/rml/tests/expected/rml-examples-011-keepwithnext.pdf
z3c/rml/tests/expected/rml-examples-017-outlines.pdf
z3c/rml/tests/expected/rml-examples-022-paras-oas.pdf
z3c/rml/tests/expected/rml-examples-029-keepinframe.pdf
z3c/rml/tests/expected/rml-examples-031-japanese.pdf
z3c_rml-5.0.1.dist-info/AUTHORS.txt
z3c_rml-5.0.1.dist-info/LICENSE.txt
z3c_rml-5.0.1.dist-info/METADATA
z3c_rml-5.0.1.dist-info/WHEEL
z3c_rml-5.0.1.dist-info/entry_points.txt
z3c_rml-5.0.1.dist-info/top_level.txt
z3c_rml-5.0.1.dist-info/RECORD
