Metadata-Version: 2.2
Name: z3c.rml
Version: 5.0.1
Summary: An alternative implementation of RML
Home-page: https://github.com/zopefoundation/z3c.rml
Author: Stephan Richter and the Zope Community
Author-email: zope-dev@zope.dev
License: ZPL-2.1
Keywords: rml reportlab pdf pagetemplate
Classifier: Development Status :: 5 - Production/Stable
Classifier: Intended Audience :: Developers
Classifier: License :: OSI Approved :: Zope Public License
Classifier: Programming Language :: Python
Classifier: Programming Language :: Python :: 3
Classifier: Programming Language :: Python :: 3.9
Classifier: Programming Language :: Python :: 3.10
Classifier: Programming Language :: Python :: 3.11
Classifier: Programming Language :: Python :: 3.12
Classifier: Programming Language :: Python :: 3.13
Classifier: Programming Language :: Python :: Implementation :: CPython
Classifier: Natural Language :: English
Classifier: Operating System :: OS Independent
Requires-Python: >=3.9
License-File: LICENSE.txt
License-File: AUTHORS.txt
Requires-Dist: Pygments
Requires-Dist: backports.tempfile
Requires-Dist: lxml
Requires-Dist: pikepdf>=3.0
Requires-Dist: reportlab>=3.5.0
Requires-Dist: rlPyCairo
Requires-Dist: setuptools
Requires-Dist: svglib
Requires-Dist: zope.interface
Requires-Dist: zope.schema
Provides-Extra: test
Requires-Dist: mock; extra == "test"
Requires-Dist: Pillow; extra == "test"
Requires-Dist: coverage; extra == "test"
Requires-Dist: zope.pagetemplate; extra == "test"
Requires-Dist: zope.testrunner>=6.4; extra == "test"
Provides-Extra: pagetemplate
Requires-Dist: zope.pagetemplate; extra == "pagetemplate"
Dynamic: author
Dynamic: author-email
Dynamic: classifier
Dynamic: description
Dynamic: home-page
Dynamic: keywords
Dynamic: license
Dynamic: provides-extra
Dynamic: requires-dist
Dynamic: requires-python
Dynamic: summary
